ekz/__init__.py
ekz/asgi.py
ekz/settings.py
ekz/urls.py
ekz/wsgi.py
front/__init__.py
front/admin.py
front/apps.py
front/backends.py
front/forms.py
front/models.py
front/tests.py
front/views.py
front/__pycache__/__init__.cpython-312.pyc
front/__pycache__/__init__.cpython-313.pyc
front/__pycache__/admin.cpython-312.pyc
front/__pycache__/admin.cpython-313.pyc
front/__pycache__/apps.cpython-312.pyc
front/__pycache__/apps.cpython-313.pyc
front/__pycache__/backends.cpython-312.pyc
front/__pycache__/backends.cpython-313.pyc
front/__pycache__/forms.cpython-312.pyc
front/__pycache__/forms.cpython-313.pyc
front/__pycache__/models.cpython-312.pyc
front/__pycache__/models.cpython-313.pyc
front/__pycache__/views.cpython-312.pyc
front/__pycache__/views.cpython-313.pyc
front/migrations/0001_initial.py
front/migrations/0002_customuser_avatar_alter_customuser_address_and_more.py
front/migrations/0003_alter_customuser_email_alter_customuser_first_name_and_more.py
front/migrations/0004_category_application_forumtopic_forumcomment_news_and_more.py
front/migrations/0005_table_tablereservation.py
front/migrations/__init__.py
front/migrations/__pycache__/0001_initial.cpython-312.pyc
front/migrations/__pycache__/0001_initial.cpython-313.pyc
front/migrations/__pycache__/0002_alter_customuser_options_customuser_education_and_more.cpython-312.pyc
front/migrations/__pycache__/0002_customuser_avatar_alter_customuser_address_and_more.cpython-312.pyc
front/migrations/__pycache__/0002_customuser_avatar_alter_customuser_address_and_more.cpython-313.pyc
front/migrations/__pycache__/0003_alter_customuser_email_alter_customuser_first_name_and_more.cpython-312.pyc
front/migrations/__pycache__/0003_alter_customuser_email_alter_customuser_first_name_and_more.cpython-313.pyc
front/migrations/__pycache__/0003_alter_customuser_options_alter_customuser_address_and_more.cpython-312.pyc
front/migrations/__pycache__/0004_alter_customuser_managers_and_more.cpython-312.pyc
django_imageskit_plus-2.0.0.dist-info/METADATA
django_imageskit_plus-2.0.0.dist-info/WHEEL
django_imageskit_plus-2.0.0.dist-info/top_level.txt
django_imageskit_plus-2.0.0.dist-info/RECORD
