Metadata-Version: 2.4
Name: django-imageskit-plus
Version: 2.0.0
Summary: django-imageskit
Author-email: viruss <viruss@email.com>
Requires-Dist: Django>=4.0
Requires-Dist: Pillow>=9.0
